django_settings_startup/__init__.py
django_settings_startup/management/__init__.py
django_settings_startup/management/commands/__init__.py
django_settings_startup/management/commands/runserver.py
django_settings_startup-2.0.dist-info/RECORD
django_settings_startup-2.0.dist-info/top_level.txt
django_settings_startup-2.0.dist-info/WHEEL
django_settings_startup-2.0.dist-info/METADATA
django_settings_startup-2.0.dist-info/metadata.json
django_settings_startup-2.0.dist-info/DESCRIPTION.rst
