Metadata-Version: 2.0
Name: django-settings-startup
Version: 2.0
Summary: A simple Django app to see settings on startup.
Home-page: https://github.com/glegoux/django-settings-startup/
Author: Gilles LEGOUX
Author-email: gilles.legoux@gmail.com
License: The MIT License (MIT)
